app/__init__.py
app/exceptions.py
app/mylogger.py
app/utils.py
app/eluent_curve/__init__.py
app/eluent_curve/api.py
app/eluent_curve/schemas.py
app/main/__init__.py
app/main/v1/__init__.py
app/main/v1/api.py
app/main/v1/schemas.py
app/main/v2/__init__.py
app/main/v2/api.py
app/main/v2/schemas.py
app/users/__init__.py
app/users/routes.py
app/users/schemas.py
pump/__init__.py
test/__init__.py
test/test_eluent_curve.py
test/test_main.py
test/test_users.py
chromayograph-1.0.0.dist-info/METADATA
chromayograph-1.0.0.dist-info/WHEEL
chromayograph-1.0.0.dist-info/entry_points.txt
chromayograph-1.0.0.dist-info/top_level.txt
chromayograph-1.0.0.dist-info/RECORD
