Metadata-Version: 2.1
Name: chromayograph
Version: 1.0.0
Summary: A brief description of your project
Home-page: https://github.com/yue000103/Chromatograph.git
Author: Zhao Xin Yue
Author-email: zhaoxinyue@pku.edu.cn
Classifier: Development Status :: 4 - Beta
Classifier: Intended Audience :: Developers
Classifier: License :: OSI Approved :: MIT License
Classifier: Programming Language :: Python :: 3.8
Requires-Dist: Flask
Requires-Dist: requests
